{
    "alpha": 0.01,
    "automatic-target-stack": 1,
    "bias-field-correction": 1,
    "date": "2021-02-19 03:26:33",
    "dir-output": "srr1",
    "filenames": [
        "nifti/Patient_8586291_109.nii.gz",
        "nifti/Patient_8586291_130.nii.gz",
        "nifti/Patient_8586291_152.nii.gz"
    ],
    "filenames-masks": [
        "seg/Patient_8586291_109_seg.nii.gz",
        "seg/Patient_8586291_130_seg.nii.gz",
        "seg/Patient_8586291_152_seg.nii.gz"
    ],
    "initial-transform": null,
    "intensity-correction": 1,
    "interleave": 3,
    "isotropic-resolution": null,
    "iter-max": 10,
    "log-config": 1,
    "multiresolution": 0,
    "outlier-rejection": 1,
    "prefix-output": "srr_",
    "reference": null,
    "reference-mask": null,
    "run-bias-field-correction": 1,
    "run-diagnostics": 0,
    "run-recon-subject-space": 1,
    "run-recon-template-space": 1,
    "s2v-hierarchical": false,
    "sda": false,
    "search-angle": 180,
    "slice-thicknesses": null,
    "suffix-mask": "",
    "target-stack": null,
    "template": null,
    "template-mask": null,
    "threshold": 0.8,
    "threshold-first": 0.5,
    "two-step-cycles": 3,
    "user": "niftymic @ virtualbox (Python 3.6.7, Linux, 4.15.0-135-generic, #139-Ubuntu SMP Mon Jan 18 17:38:24 UTC 2021, x86_64, x86_64)",
    "v2v-robust": false,
    "verbose": 0,
    "version": "0.8.0"
}